<?xml version="1.0" encoding="UTF-8"?>
<examen codeCours="006"><titre>Algebre</titre><date mois="Oct" annee="2003"/><questions><question><partie>partie1 contenu</partie><partie>partie 1question 1 contenu</partie></question><question><partie>partie1 question2</partie><partie>partie2 question2</partie><partie>partie3 question2</partie></question><question><partie>partie1 quetsion3</partie></question><question><partie>question 4 partie1</partie></question><question><partie>eez</partie><partie>dez</partie><partie>dezdzedzd</partie><partie>question 6</partie></question><question/></questions></examen>
